movidesk_client/__init__.py
movidesk_client/client.py
movidesk_client-1.0.1.dist-info/LICENSE
movidesk_client-1.0.1.dist-info/METADATA
movidesk_client-1.0.1.dist-info/WHEEL
movidesk_client-1.0.1.dist-info/top_level.txt
movidesk_client-1.0.1.dist-info/RECORD
