Metadata-Version: 2.1
Name: movidesk-client
Version: 1.0.1
Summary: A simple client to access API of the Movidesk
Home-page: https://github.com/daniellbastos/movidesk-client/
Author: Daniel Bastos
Author-email: contato@daniellbastos.com.br
License: UNKNOWN
Keywords: client,movidesk
Platform: UNKNOWN
Classifier: Programming Language :: Python :: 3.5
Classifier: Programming Language :: Python :: 3.6
Classifier: Programming Language :: Python :: 3.7
Classifier: Programming Language :: Python :: 3.8
Classifier: Programming Language :: Python :: 3.9
Classifier: Topic :: Software Development :: Libraries
